utopian_read_docx2/__init__.py
utopian_read_docx2-0.1.0.dist-info/METADATA
utopian_read_docx2-0.1.0.dist-info/WHEEL
utopian_read_docx2-0.1.0.dist-info/entry_points.txt
utopian_read_docx2-0.1.0.dist-info/RECORD
