Metadata-Version: 2.4
Name: utopian-read-docx2
Version: 0.1.0
Summary: Add your description here
Author-email: wxp <690327906@qq.com>
Requires-Python: >=3.13
Requires-Dist: docx2txt>=0.9
Requires-Dist: mcp[cli]>=1.9.4
